{"id": "gr_beyza-kahvalti-evi-fatih-sehremini", "menu": {"Ayvalık Ekmeğine Tost": [{"n": "Ayvalık Tostu", "p": {"getir": 250}, "k": "main", "ks": "r_main_strong_tokens"}, {"n": "Kavurma Kaşarlı Tost", "p": {"getir": 250}, "k": "main", "ks": "r_main_name_regex"}, {"n": "Kaşarlı Sucuklu Tost", "p": {"getir": 180}, "k": "main", "ks": "r_main_name_regex"}, {"n": "Kaşarlı Tost", "p": {"getir": 160}, "k": "main", "ks": "r_main_name_regex"}, {"n": "Yengen Tost", "p": {"getir": 210}, "k": "main", "ks": "r_main_name_regex"}, {"n": "Çift Kaşarlı Tost", "p": {"getir": 180}, "k": "main", "ks": "r_main_name_regex"}], "Ekmek Arası Kahvaltılık": [{"n": "Atom Sandviç", "p": {"getir": 240}, "k": "main", "ks": "r_main_name_regex"}, {"n": "Beyaz Sandviç", "p": {"getir": 170}, "k": "main", "ks": "r_main_name_regex"}, {"n": "Classıc Sandviç", "p": {"getir": 190}, "k": "main", "ks": "r_main_name_regex"}, {"n": "Geleneksel Sandviç", "p": {"getir": 190}, "k": "main", "ks": "r_main_name_regex"}, {"n": "Karışık Soğuk Sandviç", "p": {"getir": 230}, "k": "main", "ks": "r_main_name_regex"}, {"n": "Sosis Sandviç", "p": {"getir": 190}, "k": "main", "ks": "r_main_name_regex"}, {"n": "Ton Balıklı Sandviç", "p": {"getir": 240}, "k": "main", "ks": "r_main_name_regex"}, {"n": "Yumurtalı Sandviç", "p": {"getir": 190}, "k": "main", "ks": "r_main_name_regex"}], "Gözleme": [{"n": "Kaşarlı Gözleme", "p": {"getir": 180}, "k": "main", "ks": "r_main_mcat"}], "Kahvaltılık": [{"n": "Menemen", "p": {"getir": 150}, "k": "breakfast", "ks": "r_breakfast_mcat"}, {"n": "Omlet", "p": {"getir": 120}, "k": "breakfast", "ks": "r_breakfast_mcat"}, {"n": "Sahanda Yumurta", "p": {"getir": 120}, "k": "breakfast", "ks": "r_breakfast_mcat"}], "Yan Ürün": [{"n": "Elma Dilim Patates Kızartması", "p": {"getir": 130}, "k": "extra", "ks": "noise:extra", "x": 1}, {"n": "Patates Kızartması", "p": {"getir": 130}, "k": "extra", "ks": "noise:extra", "x": 1}, {"n": "Sigara Böreği (6 Adet)", "p": {"getir": 130}, "k": "main", "ks": "r_main_strong_tokens"}, {"n": "Soğan Halkası (6 Adet)", "p": {"getir": 130}, "k": "extra", "ks": "noise:extra", "x": 1}], "İçecek": [{"n": "Cappy Şeftali (330 ml)", "p": {"getir": 90}, "k": "drink", "ks": "noise:drink", "x": 1}, {"n": "Coca-Cola (330 ml)", "p": {"getir": 90}, "k": "drink", "ks": "noise:drink", "x": 1}, {"n": "Fanta (330 ml)", "p": {"getir": 90}, "k": "drink", "ks": "noise:drink", "x": 1}, {"n": "Limonlu Soda (200 ml)", "p": {"getir": 35}, "k": "drink", "ks": "noise:drink", "x": 1}, {"n": "Soda (200 ml)", "p": {"getir": 30}, "k": "drink", "ks": "noise:drink", "x": 1}, {"n": "Sprite (250 ml)", "p": {"getir": 80}, "k": "drink", "ks": "noise:drink", "x": 1}, {"n": "Su (500 ml)", "p": {"getir": 20}, "k": "drink", "ks": "noise:drink", "x": 1}]}}