{"id": "gr_lu-shangdong-mutfagi-maltepe-cevizli", "menu": {"Başlangıç Lezzetler": [{"n": "Buharda Çin Mantısı (4 Adet)", "p": {"getir": 545}, "k": "main", "ks": "r_main_strong_tokens"}, {"n": "Corn Tempura", "p": {"getir": 598}, "k": "other", "kc": 0.5}, {"n": "Edamame", "p": {"getir": 376}, "k": "other", "kc": 0.5}, {"n": "Eggplant Rocket", "p": {"getir": 568}, "k": "other", "kc": 0.5}, {"n": "Etli Gyoza (5 Adet)", "p": {"getir": 584}, "k": "other", "kc": 0.5}, {"n": "Etli Çin Böregi (2 Adet)", "p": {"getir": 401}, "k": "other", "kc": 0.5}, {"n": "Karides Cipsi", "p": {"getir": 340}, "k": "other", "kc": 0.5}, {"n": "Karides Topları (6 Adet)", "p": {"getir": 691}, "k": "other", "kc": 0.5}, {"n": "Karidesli Gyoza (5 Adet)", "p": {"getir": 628}, "k": "other", "kc": 0.5}, {"n": "Korean Buharda Mantı (4 Adet)", "p": {"getir": 584}, "k": "main", "ks": "r_main_name_regex"}, {"n": "Shrimp Börek", "p": {"getir": 482}, "k": "bakery", "ks": "r_bakery_name_token"}, {"n": "Spicy Edamame (Acılı)", "p": {"getir": 377}, "k": "other", "kc": 0.5}, {"n": "Sweet Patato", "p": {"getir": 578}, "k": "other", "kc": 0.5}, {"n": "Tavuk Topları (6 Adet)", "p": {"getir": 575}, "k": "main", "ks": "r_main_name_regex"}, {"n": "Çin Böreği Sebzeli (2 Adet)", "p": {"getir": 370}, "k": "main", "ks": "r_main_strong_tokens"}, {"n": "Çıtır Pane Tavuk (10 Adet)", "p": {"getir": 690}, "k": "main", "ks": "r_main_name_regex"}, {"n": "Çıtır Tavuk & Salata", "p": {"getir": 662}, "k": "main", "ks": "r_main_name_regex"}, {"n": "Çıtır Çin Mantısı (4 Adet)", "p": {"getir": 545}, "k": "main", "ks": "r_main_strong_tokens"}, {"n": "Ördekli Çin Böreği (2 Adet)", "p": {"getir": 436}, "k": "main", "ks": "r_main_strong_tokens"}], "Chirashi Bowl": [{"n": "Dana Etli Bowl", "p": {"getir": 1166}, "k": "other", "kc": 0.5}, {"n": "Ebi Chirashi Bowl", "p": {"getir": 979}, "k": "other", "kc": 0.5}, {"n": "Kani Chirashi Bowl", "p": {"getir": 974}, "k": "other", "kc": 0.5}, {"n": "Maguro Chirashi Bowl", "p": {"getir": 1006}, "k": "other", "kc": 0.5}, {"n": "Sake Chirashi Bowl", "p": {"getir": 976}, "k": "other", "kc": 0.5}, {"n": "Suzuki Chirashi Bowl", "p": {"getir": 975}, "k": "other", "kc": 0.5}, {"n": "Unagi Chirashi Bowl", "p": {"getir": 1049}, "k": "other", "kc": 0.5}], "Dana Etleri": [{"n": "Acılı Mantarlı Dana Eti", "p": {"getir": 1166}, "k": "other", "kc": 0.5}, {"n": "Beyaz Mantarlı Dana Eti", "p": {"getir": 1166}, "k": "other", "kc": 0.5}, {"n": "Brokolili Dana Eti", "p": {"getir": 1166}, "k": "other", "kc": 0.5}, {"n": "Karabiber Soslu Dana Eti", "p": {"getir": 1166}, "k": "other", "kc": 0.5}, {"n": "Karışık Sebzeli Dana Eti", "p": {"getir": 1166}, "k": "other", "kc": 0.5}, {"n": "Kuru Soğanlı Dana Eti", "p": {"getir": 1166}, "k": "other", "kc": 0.5}, {"n": "Kuşkonmazlı Dana Eti", "p": {"getir": 1186}, "k": "other", "kc": 0.5}, {"n": "Limon Soslu Çıtır Dana Eti", "p": {"getir": 1186}, "k": "other", "kc": 0.5}, {"n": "Sarımsak Soslu Dana Eti", "p": {"getir": 1166}, "k": "other", "kc": 0.5}, {"n": "Siyah Çin Mantarlı Dana Eti", "p": {"getir": 1166}, "k": "other", "kc": 0.5}, {"n": "Yeşil Biberli Dana Eti", "p": {"getir": 1166}, "k": "other", "kc": 0.5}, {"n": "Çıtır Patlıcanlı Dana Eti", "p": {"getir": 1186}, "k": "other", "kc": 0.5}, {"n": "İnce Kıyım Biberli Dana Eti", "p": {"getir": 1166}, "k": "other", "kc": 0.5}, {"n": "İstridye Soslu Dana Eti", "p": {"getir": 1166}, "k": "other", "kc": 0.5}], "Deniz Mahsulleri": [{"n": "Acı Soslu Karides (7 Adet)", "p": {"getir": 1186}, "k": "other", "kc": 0.5}, {"n": "Acılı Fıstıklı Kalamar", "p": {"getir": 1164}, "k": "other", "kc": 0.5}, {"n": "Izgara Levrek", "p": {"getir": 1166}, "k": "main", "ks": "r_main_name_regex"}, {"n": "Izgara Somon", "p": {"getir": 1186}, "k": "main", "ks": "r_main_name_regex"}, {"n": "Karışık Sebzeli Ahtapot", "p": {"getir": 1166}, "k": "other", "kc": 0.5}, {"n": "Karışık Sebzeli Karides (7 Adet)", "p": {"getir": 1186}, "k": "other", "kc": 0.5}, {"n": "Kung Pao Karides", "p": {"getir": 1186}, "k": "other", "kc": 0.5}, {"n": "Köri Soslu Jumbo Karides", "p": {"getir": 1186}, "k": "other", "kc": 0.5}, {"n": "Spesiyal Soslu Acılı Jumbo Karides", "p": {"getir": 1186}, "k": "other", "kc": 0.5}, {"n": "Spesiyal Soslu Acılı Kalamar", "p": {"getir": 1164}, "k": "other", "kc": 0.5}, {"n": "Tatlı Ekşi Soslu Jumbo Karides", "p": {"getir": 1186}, "k": "other", "kc": 0.5}, {"n": "Zencefil Soslu Çıtır Levrek", "p": {"getir": 1166}, "k": "other", "kc": 0.5}, {"n": "Zencefil Soslı Çıtır Mezgit (Acılı)", "p": {"getir": 1163}, "k": "other", "kc": 0.5}], "Ekstra Lezzet": [{"n": "Chopstick", "p": {"getir": 69}, "k": "extra", "ks": "noise:extra", "x": 1}, {"n": "Chopstick Aparatı", "p": {"getir": 69}, "k": "extra", "ks": "noise:extra", "x": 1}, {"n": "Ördek Yufkası (Pankek 6 Adet)", "p": {"getir": 111}, "k": "extra", "ks": "noise:extra", "x": 1}, {"n": "Şans Kurabiyesi", "p": {"getir": 69}, "k": "extra", "ks": "noise:extra", "x": 1}], "Erişte Üstü Tat": [{"n": "Sebzeli Erişte Üstü & Zencefil Soslu Çıtır Tavuk", "p": {"getir": 1082}, "k": "main", "ks": "r_main_name_regex"}, {"n": "Sebzeli Erişte Üstü Acılı Mantarlı Dana Eti", "p": {"getir": 1244}, "k": "other", "kc": 0.5}, {"n": "Sebzeli Erişte Üstü Bademli Tavuk", "p": {"getir": 1082}, "k": "main", "ks": "r_main_name_regex"}, {"n": "Sebzeli Erişte Üstü Beyaz Mantarlı Tavuk", "p": {"getir": 1082}, "k": "main", "ks": "r_main_name_regex"}, {"n": "Sebzeli Erişte Üstü General Tso Tavuk", "p": {"getir": 1082}, "k": "main", "ks": "r_main_name_regex"}, {"n": "Sebzeli Erişte Üstü Kung Pao Tavuk", "p": {"getir": 1082}, "k": "main", "ks": "r_main_name_regex"}, {"n": "Sebzeli Erişte Üstü Kuşkonmazlı Dana Eti", "p": {"getir": 1244}, "k": "other", "kc": 0.5}, {"n": "Sebzeli Erişte Üstü Mançuryan Usulü Tavuk", "p": {"getir": 1082}, "k": "main", "ks": "r_main_name_regex"}, {"n": "Sebzeli Erişte Üstü Sarımsak Soslu Dana Eti", "p": {"getir": 1244}, "k": "other", "kc": 0.5}, {"n": "Sebzeli Erişte Üstü Siyah Mantarlı Acılı Tavuk", "p": {"getir": 1082}, "k": "main", "ks": "r_main_name_regex"}, {"n": "Sebzeli Erişte Üstü Siyah Çin Mantarlı Dana Eti", "p": {"getir": 1244}, "k": "other", "kc": 0.5}, {"n": "Sebzeli Erişte Üstü Spesiyal Acılı Tavuk", "p": {"getir": 1082}, "k": "main", "ks": "r_main_name_regex"}, {"n": "Sebzeli Erişte Üstü Tatlı Ekşi Soslu Tavuk", "p": {"getir": 1082}, "k": "main", "ks": "r_main_name_regex"}, {"n": "Sebzeli Erişte Üstü Teriyaki Soslu Tavuk", "p": {"getir": 1082}, "k": "main", "ks": "r_main_name_regex"}, {"n": "Sebzeli Erişte Üstü Thai Usulü Kaju Fıstıklı Tavuk", "p": {"getir": 1082}, "k": "main", "ks": "r_main_name_regex"}, {"n": "Sebzeli Erişte Üstü Yeşil Biberli Dana Eti", "p": {"getir": 1244}, "k": "other", "kc": 0.5}, {"n": "Sebzeli Erişte Üstü İnce Kıyım Biberli Dana Eti", "p": {"getir": 1244}, "k": "other", "kc": 0.5}, {"n": "Sebzeli Erişte Üstü İstiridye Soslu Dana Eti", "p": {"getir": 1244}, "k": "other", "kc": 0.5}], "Japon Makarnası": [{"n": "Dana Etli Sebzeli Udon", "p": {"getir": 974}, "k": "other", "kc": 0.5}, {"n": "Etli Udon (Kore Usulü)", "p": {"getir": 976}, "k": "other", "kc": 0.5}, {"n": "Karidesli Sebzeli Udon", "p": {"getir": 1007}, "k": "other", "kc": 0.5}, {"n": "Karışık (Mix) Sebzeli Udon", "p": {"getir": 1009}, "k": "other", "kc": 0.5}, {"n": "Kore Usulü Bulgogi Dana Udon", "p": {"getir": 974}, "k": "other", "kc": 0.5}, {"n": "Kore Usulü Tavuklu Bulgogi Udon", "p": {"getir": 881}, "k": "main", "ks": "r_main_strong_tokens"}, {"n": "Sarımsaklı Etli Udon", "p": {"getir": 976}, "k": "other", "kc": 0.5}, {"n": "Sebzeli Udon", "p": {"getir": 827}, "k": "other", "kc": 0.5}, {"n": "Siyah Sarımsaklı Dana Udon", "p": {"getir": 976}, "k": "other", "kc": 0.5}, {"n": "Siyah Sarımsaklı Udon", "p": {"getir": 830}, "k": "other", "kc": 0.5}, {"n": "Tavuklu Sebzeli Udon", "p": {"getir": 878}, "k": "main", "ks": "r_main_strong_tokens"}, {"n": "Tavuklu Udon (Kore Usulü)", "p": {"getir": 881}, "k": "main", "ks": "r_main_strong_tokens"}], "Kayzen Best Rolls": [{"n": "Bonito Roll (8 Pcs.)", "p": {"getir": 836}, "k": "other", "kc": 0.5}, {"n": "Boston Roll (8 Pcs.)", "p": {"getir": 836}, "k": "other", "kc": 0.5}, {"n": "California Ebi Roll (8 Pcs.)", "p": {"getir": 836}, "k": "other", "kc": 0.5}, {"n": "California Roll (8 Pcs.)", "p": {"getir": 836}, "k": "other", "kc": 0.5}, {"n": "California Sake Roll (8 Pcs.)", "p": {"getir": 836}, "k": "other", "kc": 0.5}, {"n": "California Unagi Roll (8 Pcs.)", "p": {"getir": 872}, "k": "other", "kc": 0.5}, {"n": "Dragon Roll (8 Pcs.)", "p": {"getir": 872}, "k": "other", "kc": 0.5}, {"n": "Envı Roll (8 Pcs.)", "p": {"getir": 872}, "k": "other", "kc": 0.5}, {"n": "Kayzen Roll (8 Pcs.)", "p": {"getir": 839}, "k": "other", "kc": 0.5}, {"n": "Lava Roll (8 Pcs.)", "p": {"getir": 836}, "k": "other", "kc": 0.5}, {"n": "NewYork Roll (8 Pcs.)", "p": {"getir": 836}, "k": "other", "kc": 0.5}, {"n": "Philadelphia Lite Roll (8 Pcs.)", "p": {"getir": 836}, "k": "other", "kc": 0.5}, {"n": "Philadelphia Roll (8 Pcs.)", "p": {"getir": 836}, "k": "other", "kc": 0.5}, {"n": "Piramida Roll (8 Pcs.)", "p": {"getir": 836}, "k": "other", "kc": 0.5}, {"n": "Rainbow Roll (8 Pcs.)", "p": {"getir": 872}, "k": "other", "kc": 0.5}, {"n": "Rock`N Roll (8 Pcs.)", "p": {"getir": 872}, "k": "other", "kc": 0.5}, {"n": "Romeo & Juliet Roll (8 Pcs.)", "p": {"getir": 836}, "k": "other", "kc": 0.5}, {"n": "Spicy Tuna Roll (8 Pcs.)", "p": {"getir": 836}, "k": "other", "kc": 0.5}, {"n": "Tartar Roll (8 Pcs.)", "p": {"getir": 836}, "k": "other", "kc": 0.5}, {"n": "Tiger Roll (8 Pcs.)", "p": {"getir": 872}, "k": "other", "kc": 0.5}, {"n": "İnyan Roll (8 Pcs.)", "p": {"getir": 872}, "k": "other", "kc": 0.5}], "Kayzen Box Menü": [{"n": "Dana Etli Box Menü", "p": {"getir": 1468}, "k": "combo", "ks": "r_combo_name_price"}, {"n": "Dana Etli Set Menü", "p": {"getir": 1540}, "k": "combo", "ks": "r_combo_name_price"}, {"n": "Karidesli Box Menü", "p": {"getir": 1531}, "k": "combo", "ks": "r_combo_name_price"}, {"n": "Kayzen Box Menü 1", "p": {"getir": 1669}, "k": "combo", "ks": "r_combo_name_price"}, {"n": "Kayzen Box Menü 2", "p": {"getir": 1602}, "k": "combo", "ks": "r_combo_name_price"}, {"n": "Kayzen Box Menü 3", "p": {"getir": 1759}, "k": "combo", "ks": "r_combo_name_price"}, {"n": "Tavuklu Box Menü", "p": {"getir": 1209}, "k": "combo", "ks": "r_combo_name_price"}, {"n": "Tavuklu Set Menü", "p": {"getir": 1424}, "k": "combo", "ks": "r_combo_name_price"}, {"n": "Vegan Set Menü", "p": {"getir": 1160}, "k": "combo", "ks": "r_combo_name_price"}], "Kayzen Hot Rolls": [{"n": "Bali Roll (8 Pcs.)", "p": {"getir": 872}, "k": "other", "kc": 0.5}, {"n": "Chicken Roll (8 Pcs.)", "p": {"getir": 836}, "k": "other", "kc": 0.5}, {"n": "Crispy Roll (8 Pcs.)", "p": {"getir": 836}, "k": "other", "kc": 0.5}, {"n": "Crunchy Ebi Roll (8 Pcs.)", "p": {"getir": 836}, "k": "other", "kc": 0.5}, {"n": "Crunchy Sake Roll (8 Pcs.)", "p": {"getir": 836}, "k": "other", "kc": 0.5}, {"n": "Crunchy Suzuki Roll (8 Pcs.)", "p": {"getir": 836}, "k": "other", "kc": 0.5}, {"n": "Dinamit Karides Roll (8 Pcs.)", "p": {"getir": 836}, "k": "other", "kc": 0.5}, {"n": "Ebi Ten Roll (8 Pcs.)", "p": {"getir": 836}, "k": "other", "kc": 0.5}, {"n": "Ebi Ten Trüflü Roll (8 Pcs.)", "p": {"getir": 836}, "k": "other", "kc": 0.5}, {"n": "Fish Roll (8 Pcs.)", "p": {"getir": 839}, "k": "other", "kc": 0.5}, {"n": "Mirani Roll (8 Pcs.)", "p": {"getir": 836}, "k": "other", "kc": 0.5}, {"n": "Ronin Roll (8 Pcs.)", "p": {"getir": 836}, "k": "other", "kc": 0.5}, {"n": "Sake Ten Roll (8 Pcs.)", "p": {"getir": 836}, "k": "other", "kc": 0.5}, {"n": "Sesame Roll (8 Pcs.)", "p": {"getir": 836}, "k": "other", "kc": 0.5}, {"n": "Tokyo Roll (8 Pcs.)", "p": {"getir": 836}, "k": "other", "kc": 0.5}, {"n": "Zapechenney Ebi Tempura (8 Pcs.)", "p": {"getir": 838}, "k": "other", "kc": 0.5}, {"n": "Zapechenney Sake Tempura (8 Pcs.)", "p": {"getir": 838}, "k": "other", "kc": 0.5}, {"n": "Zapechenney Unagi Tempura (8 Pcs.)", "p": {"getir": 872}, "k": "other", "kc": 0.5}, {"n": "İstanbul Roll (8 Pcs.)", "p": {"getir": 839}, "k": "other", "kc": 0.5}], "Kayzen Maki Rolls": [{"n": "Avokado Maki Roll (6 Pcs.)", "p": {"getir": 399}, "k": "other", "kc": 0.5}, {"n": "Ebi Maki Roll (6 Pcs.)", "p": {"getir": 556}, "k": "other", "kc": 0.5}, {"n": "Kani Maki Roll (6 Pcs.)", "p": {"getir": 494}, "k": "other", "kc": 0.5}, {"n": "Kappa Maki Roll (6 Pcs.)", "p": {"getir": 363}, "k": "other", "kc": 0.5}, {"n": "Maguro Maki Roll (6 Pcs.)", "p": {"getir": 598}, "k": "other", "kc": 0.5}, {"n": "Sake Maki Roll (6 Pcs.)", "p": {"getir": 546}, "k": "other", "kc": 0.5}, {"n": "Suzuki Maki Roll (6 Pcs.)", "p": {"getir": 542}, "k": "other", "kc": 0.5}, {"n": "Unagi Maki Roll (6 Pcs.)", "p": {"getir": 626}, "k": "other", "kc": 0.5}], "Kayzen Special Rolls": [{"n": "Canadian Roll (8 Pcs.)", "p": {"getir": 836}, "k": "other", "kc": 0.5}, {"n": "Sake Cream Cheese Roll (8 Pcs.)", "p": {"getir": 836}, "k": "other", "kc": 0.5}, {"n": "Salmon California Roll (8 Pcs.)", "p": {"getir": 836}, "k": "other", "kc": 0.5}, {"n": "San Diago Roll (8 Pcs.)", "p": {"getir": 836}, "k": "other", "kc": 0.5}, {"n": "Spicy Philadelphia Roll (8 Pcs.)", "p": {"getir": 836}, "k": "other", "kc": 0.5}], "Kayzen Tempura Rolls": [{"n": "Corn Tempura Roll (8 Pcs.)", "p": {"getir": 825}, "k": "other", "kc": 0.5}, {"n": "Kayzen Tempura Maki Roll (8 Pcs.)", "p": {"getir": 818}, "k": "other", "kc": 0.5}, {"n": "Sake Lava Tempura Maki Roll (8 Pcs.)", "p": {"getir": 814}, "k": "other", "kc": 0.5}, {"n": "Sake Unagi Tempura Maki Roll (8 Pcs.)", "p": {"getir": 818}, "k": "other", "kc": 0.5}, {"n": "Sezar Tempura (8 Pcs.)", "p": {"getir": 813}, "k": "other", "kc": 0.5}, {"n": "Sunami Tempura Maki Roll (8 Pcs.)", "p": {"getir": 816}, "k": "other", "kc": 0.5}, {"n": "Tori Tempura Maki Roll (8 Pcs.)", "p": {"getir": 811}, "k": "other", "kc": 0.5}, {"n": "Vegas Tempura Maki Roll (8 Pcs.)", "p": {"getir": 817}, "k": "other", "kc": 0.5}, {"n": "Yakuza Tempura (8 Pcs.)", "p": {"getir": 811}, "k": "other", "kc": 0.5}], "Kore Makarnaları": [{"n": "Pad Thai Dana", "p": {"getir": 953}, "k": "other", "kc": 0.5}, {"n": "Pad Thai Karides", "p": {"getir": 975}, "k": "other", "kc": 0.5}, {"n": "Pad Thai Tavuk", "p": {"getir": 850}, "k": "main", "ks": "r_main_name_regex"}], "Mochi Japon Tatlı": [{"n": "Hindistan Cevizli Dondurmalı Mochi", "p": {"getir": 158}, "k": "other", "kc": 0.5}, {"n": "Karadutlu Dondurmalı Mochi (35 g)", "p": {"getir": 158}, "k": "other", "kc": 0.5}, {"n": "Karamelli Dondurmalı Mochi (35 g)", "p": {"getir": 158}, "k": "other", "kc": 0.5}, {"n": "Kavunlu Mochi Tatlısı (35 g)", "p": {"getir": 158}, "k": "other", "kc": 0.5}, {"n": "Kitkat Çikolatalı Dondurmalı Mochi (35 g)", "p": {"getir": 158}, "k": "other", "kc": 0.5}, {"n": "Limonlu Dondurmalı Mochi (35 g)", "p": {"getir": 158}, "k": "other", "kc": 0.5}, {"n": "Mangolu Dondurmalı Mochi (35 g)", "p": {"getir": 158}, "k": "other", "kc": 0.5}, {"n": "Sakızlı (Bubble Gum) Dondurmalı Mochi (35 g)", "p": {"getir": 158}, "k": "other", "kc": 0.5}, {"n": "Vanilyalı Dondurmalı Mochi (35 g)", "p": {"getir": 158}, "k": "other", "kc": 0.5}, {"n": "Yaban Mersinli Dondurmalı Mochi (35 g)", "p": {"getir": 158}, "k": "other", "kc": 0.5}, {"n": "Çilekli Dondurmalı Mochi (35 g)", "p": {"getir": 158}, "k": "other", "kc": 0.5}], "Nigiri Sushi": [{"n": "Ebi Nigiri (1 Pcs.)", "p": {"getir": 172}, "k": "other", "kc": 0.5}, {"n": "Kani Nigiri (1 Pcs.)", "p": {"getir": 150}, "k": "other", "kc": 0.5}, {"n": "Maguro Nigiri (1 Adet)", "p": {"getir": 220}, "k": "other", "kc": 0.5}, {"n": "Sake Nigiri (1 Pcs.)", "p": {"getir": 167}, "k": "other", "kc": 0.5}, {"n": "Suzuki Nigiri (1 Pcs.)", "p": {"getir": 150}, "k": "other", "kc": 0.5}, {"n": "Unagi Nigiri (1 Pcs.)", "p": {"getir": 229}, "k": "other", "kc": 0.5}], "Pilav Üstü Lezzet": [{"n": "Sebzeli Pilav Üstü Acılı Mantarlı Dana Eti", "p": {"getir": 1063}, "k": "main", "ks": "r_main_name_regex"}, {"n": "Sebzeli Pilav Üstü General Tso Tavuk", "p": {"getir": 905}, "k": "main", "ks": "r_main_name_regex"}, {"n": "Sebzeli Pilav Üstü Mançuryan Usulü Tavuk", "p": {"getir": 905}, "k": "main", "ks": "r_main_name_regex"}, {"n": "Sebzeli Pilav Üstü Tatlı Ekşi Soslu Tavuk", "p": {"getir": 905}, "k": "main", "ks": "r_main_name_regex"}, {"n": "Sebzeli Pilav Üstü Yeşil Biberli Dana Eti", "p": {"getir": 1063}, "k": "main", "ks": "r_main_name_regex"}, {"n": "Sebzeli Pilav Üstü İnce Kıyım Biberli Dana Eti", "p": {"getir": 1063}, "k": "main", "ks": "r_main_name_regex"}, {"n": "Sebzeli Pilav Üstü İstiridye Soslu Dana Eti", "p": {"getir": 1063}, "k": "main", "ks": "r_main_name_regex"}, {"n": "Tavuklu Pilav Üstü Acılı Kuşkonmazlı Mantar Sote", "p": {"getir": 944}, "k": "main", "ks": "r_main_name_regex"}, {"n": "Tavuklu Pilav Üstü Sarımsak Soslu Brokoli", "p": {"getir": 839}, "k": "main", "ks": "r_main_name_regex"}, {"n": "Tavuklu Pilav Üstü Sarımsak Soslu Kuşkonmaz", "p": {"getir": 942}, "k": "main", "ks": "r_main_name_regex"}, {"n": "Tavuklu Pilav Üstü Sebzeli Tofu", "p": {"getir": 946}, "k": "main", "ks": "r_main_name_regex"}, {"n": "Tavuklu Pilav Üstü Spesiyal Acılı Çin Fasulyesi", "p": {"getir": 946}, "k": "main", "ks": "r_main_name_regex"}], "Pilavlar": [{"n": "Dana Etli Sebzeli Pilav", "p": {"getir": 701}, "k": "main", "ks": "r_main_name_regex"}, {"n": "Dana Etli ve Körili Pilav", "p": {"getir": 703}, "k": "main", "ks": "r_main_name_regex"}, {"n": "Karidesli Sebzeli Pilav", "p": {"getir": 808}, "k": "main", "ks": "r_main_name_regex"}, {"n": "Sade Pilav", "p": {"getir": 399}, "k": "main", "ks": "r_main_name_regex"}, {"n": "Sebzeli Pilav", "p": {"getir": 481}, "k": "main", "ks": "r_main_name_regex"}, {"n": "Spesiyal Acılı Pilav", "p": {"getir": 509}, "k": "main", "ks": "r_main_name_regex"}, {"n": "Tavuklu & Körili Pilav", "p": {"getir": 604}, "k": "main", "ks": "r_main_name_regex"}, {"n": "Tavuklu Sebzeli Pilav", "p": {"getir": 603}, "k": "main", "ks": "r_main_name_regex"}, {"n": "Yumurtalı Sebzeli Pilav", "p": {"getir": 508}, "k": "main", "ks": "r_main_name_regex"}], "Ramenler": [{"n": "Dana Etli Sebzeli Ramen", "p": {"getir": 974}, "k": "other", "kc": 0.5}, {"n": "Karidesli Sebzeli Ramen", "p": {"getir": 997}, "k": "other", "kc": 0.5}, {"n": "Karışık (Mix) Sebzeli Ramen", "p": {"getir": 999}, "k": "other", "kc": 0.5}, {"n": "Sebzeli Ramen", "p": {"getir": 828}, "k": "other", "kc": 0.5}, {"n": "Tavuklu Sebzeli Ramen", "p": {"getir": 850}, "k": "main", "ks": "r_main_strong_tokens"}, {"n": "Tofulu Ramen", "p": {"getir": 848}, "k": "other", "kc": 0.5}, {"n": "Wonton Ramen", "p": {"getir": 848}, "k": "other", "kc": 0.5}], "Salatalar": [{"n": "Ahtapot Salatası", "p": {"getir": 836}, "k": "main", "ks": "r_main_mcat"}, {"n": "Dana Etli Salata", "p": {"getir": 629}, "k": "main", "ks": "r_main_mcat"}, {"n": "Deniz Ürünleri Salatası", "p": {"getir": 839}, "k": "main", "ks": "r_main_mcat"}, {"n": "Karidesli Salata", "p": {"getir": 839}, "k": "main", "ks": "r_main_mcat"}, {"n": "Lahana Salatası (Acılı)", "p": {"getir": 370}, "k": "main", "ks": "r_main_mcat"}, {"n": "Levrek Salatası", "p": {"getir": 1166}, "k": "main", "ks": "r_main_mcat"}, {"n": "Sashimi Salatası", "p": {"getir": 694}, "k": "main", "ks": "r_main_mcat"}, {"n": "Somon Salatası", "p": {"getir": 1186}, "k": "main", "ks": "r_main_mcat"}, {"n": "Tavuklu Salata", "p": {"getir": 598}, "k": "main", "ks": "r_main_mcat"}, {"n": "Wakame Salata", "p": {"getir": 691}, "k": "main", "ks": "r_main_mcat"}, {"n": "Yengeç Salatası", "p": {"getir": 830}, "k": "main", "ks": "r_main_mcat"}], "Sashimi Sushi": [{"n": "Ebi Sashimi (5 Pcs.)", "p": {"getir": 500}, "k": "other", "kc": 0.5}, {"n": "Maguro Sashimi (5 Pcs.)", "p": {"getir": 507}, "k": "other", "kc": 0.5}, {"n": "Sake Sashimi (5 Pcs.)", "p": {"getir": 485}, "k": "other", "kc": 0.5}, {"n": "Suzuki Sashimi (5 Pcs.)", "p": {"getir": 482}, "k": "other", "kc": 0.5}, {"n": "Unagi Sashimi (5 Pcs.)", "p": {"getir": 569}, "k": "other", "kc": 0.5}], "Sebzeler": [{"n": "Acılı Kuşkonmazlı Mantar Sote", "p": {"getir": 678}, "k": "other", "kc": 0.5}, {"n": "General Tso Tofu", "p": {"getir": 685}, "k": "other", "kc": 0.5}, {"n": "Karışık Sebze", "p": {"getir": 472}, "k": "other", "kc": 0.5}, {"n": "Sarımsak Soslu Brokoli", "p": {"getir": 472}, "k": "other", "kc": 0.5}, {"n": "Sarımsak Soslu Kuşkonmaz", "p": {"getir": 676}, "k": "other", "kc": 0.5}, {"n": "Sebzeli Tofu", "p": {"getir": 685}, "k": "other", "kc": 0.5}, {"n": "Spesiyal Acılı Çin Fasulyesi", "p": {"getir": 472}, "k": "other", "kc": 0.5}, {"n": "Çıtır Çin Fasulyesi", "p": {"getir": 472}, "k": "other", "kc": 0.5}], "Soslar": [{"n": "Erik Sos", "p": {"getir": 69}, "k": "sauce", "ks": "noise:sauce", "x": 1}, {"n": "Hoisin Sos", "p": {"getir": 69}, "k": "sauce", "ks": "noise:sauce", "x": 1}, {"n": "Sarımsak Sos", "p": {"getir": 69}, "k": "sauce", "ks": "noise:sauce", "x": 1}, {"n": "Soya Sosu", "p": {"getir": 69}, "k": "sauce", "ks": "noise:sauce", "x": 1}, {"n": "Sriracha Sos", "p": {"getir": 69}, "k": "sauce", "ks": "noise:sauce", "x": 1}, {"n": "Sweet Chili Sos", "p": {"getir": 69}, "k": "sauce", "ks": "noise:sauce", "x": 1}, {"n": "Tatlı Ekşi Sos", "p": {"getir": 69}, "k": "sauce", "ks": "noise:sauce", "x": 1}, {"n": "Teriyaki Sos", "p": {"getir": 69}, "k": "sauce", "ks": "noise:sauce", "x": 1}, {"n": "Wasabi (Adet)", "p": {"getir": 69}, "k": "sauce", "ks": "noise:sauce", "x": 1}, {"n": "Zencefil Turşusu (Adet)", "p": {"getir": 69}, "k": "sauce", "ks": "noise:sauce", "x": 1}, {"n": "Çin Acı Sos", "p": {"getir": 69}, "k": "sauce", "ks": "noise:sauce", "x": 1}, {"n": "İstiridye Sos", "p": {"getir": 69}, "k": "sauce", "ks": "noise:sauce", "x": 1}], "Special Erişteler": [{"n": "Dana Etli Sebzeli Erişte", "p": {"getir": 818}, "k": "other", "kc": 0.5}, {"n": "Karidesli Kaju Baharatlı Erişte", "p": {"getir": 882}, "k": "other", "kc": 0.5}, {"n": "Karidesli Sebzeli Erişte", "p": {"getir": 881}, "k": "other", "kc": 0.5}, {"n": "Karışık (Mix) Erişte", "p": {"getir": 883}, "k": "other", "kc": 0.5}, {"n": "Robokki", "p": {"getir": 702}, "k": "other", "kc": 0.5}, {"n": "Sade Erişte", "p": {"getir": 533}, "k": "other", "kc": 0.5}, {"n": "Sebzeli Erişte", "p": {"getir": 662}, "k": "other", "kc": 0.5}, {"n": "Singapur Sebzeli Erişte", "p": {"getir": 892}, "k": "other", "kc": 0.5}, {"n": "Tavuklu Sebzeli Erişte", "p": {"getir": 729}, "k": "main", "ks": "r_main_strong_tokens"}], "Sushi Set Menü": [{"n": "California Set l (32 Pcs.)", "p": {"getir": 2166}, "k": "other", "kc": 0.5}, {"n": "Crunchy Set (32 Pcs.)", "p": {"getir": 2169}, "k": "other", "kc": 0.5}, {"n": "Japanese Set (42 Pcs.)", "p": {"getir": 2860}, "k": "other", "kc": 0.5}, {"n": "Kayzen Set (42 Pcs.)", "p": {"getir": 2894}, "k": "other", "kc": 0.5}, {"n": "Kayzen Sushi Set 1", "p": {"getir": 1152}, "k": "other", "kc": 0.5}, {"n": "Kayzen Sushi Set 2", "p": {"getir": 1128}, "k": "other", "kc": 0.5}, {"n": "Kayzen Sushi Set 3", "p": {"getir": 1165}, "k": "other", "kc": 0.5}, {"n": "Kayzen Sushi Set 4", "p": {"getir": 1093}, "k": "other", "kc": 0.5}, {"n": "Kayzen Sushi Set 5", "p": {"getir": 1259}, "k": "other", "kc": 0.5}, {"n": "King Sushi Set (18 Pcs.)", "p": {"getir": 1522}, "k": "other", "kc": 0.5}, {"n": "Klasik Set (24 Pcs)", "p": {"getir": 1868}, "k": "other", "kc": 0.5}, {"n": "Maki Set (24 Pcs.)", "p": {"getir": 1728}, "k": "other", "kc": 0.5}, {"n": "Nigiri Set (10 Pcs)", "p": {"getir": 1198}, "k": "other", "kc": 0.5}, {"n": "Private Chef Set (18 Pcs.)", "p": {"getir": 1410}, "k": "other", "kc": 0.5}, {"n": "Sashimi Set (12 Pcs.)", "p": {"getir": 944}, "k": "other", "kc": 0.5}, {"n": "Tempura Set (32 Pcs.)", "p": {"getir": 2251}, "k": "other", "kc": 0.5}, {"n": "Vegan Maki Set (18 Pcs.) & Edamame", "p": {"getir": 1402}, "k": "other", "kc": 0.5}], "Tatlılar": [{"n": "Balda Kızarmış Ananas", "p": {"getir": 500}, "k": "dessert", "ks": "r_dessert_mcat", "x": 1}, {"n": "Balda Kızarmış Ceviz", "p": {"getir": 503}, "k": "dessert", "ks": "r_dessert_mcat", "x": 1}, {"n": "Balda Kızarmış Dondurma", "p": {"getir": 514}, "k": "dessert", "ks": "r_dessert_mcat", "x": 1}, {"n": "Balda Kızarmış Muz", "p": {"getir": 487}, "k": "dessert", "ks": "r_dessert_mcat", "x": 1}, {"n": "Belgium Sweet Roll (6 Pcs.)", "p": {"getir": 573}, "k": "dessert", "ks": "r_dessert_mcat", "x": 1}], "Tavuklar": [{"n": "Acılı Patlıcanlı Tavuk", "p": {"getir": 848}, "k": "main", "ks": "r_main_name_regex"}, {"n": "Bademli Tavuk", "p": {"getir": 839}, "k": "main", "ks": "r_main_name_regex"}, {"n": "Beyaz Mantarlı Tavuk", "p": {"getir": 838}, "k": "main", "ks": "r_main_name_regex"}, {"n": "General Tso Tavuk", "p": {"getir": 848}, "k": "main", "ks": "r_main_name_regex"}, {"n": "Karışık Sebzeli Tavuk", "p": {"getir": 838}, "k": "main", "ks": "r_main_name_regex"}, {"n": "Kung Pao Tavuk", "p": {"getir": 838}, "k": "main", "ks": "r_main_name_regex"}, {"n": "Mançuryan Tavuk", "p": {"getir": 839}, "k": "main", "ks": "r_main_name_regex"}, {"n": "Mu Shu Tavuk", "p": {"getir": 848}, "k": "main", "ks": "r_main_name_regex"}, {"n": "Shangai Tavuk", "p": {"getir": 838}, "k": "main", "ks": "r_main_name_regex"}, {"n": "Siyah Mantarlı Acılı Tavuk", "p": {"getir": 848}, "k": "main", "ks": "r_main_name_regex"}, {"n": "Spesiyal Acılı Tavuk", "p": {"getir": 838}, "k": "main", "ks": "r_main_name_regex"}, {"n": "Tatlı Ekşi Soslu Tavuk", "p": {"getir": 838}, "k": "main", "ks": "r_main_name_regex"}, {"n": "Teriyaki Soslu Tavuk", "p": {"getir": 838}, "k": "main", "ks": "r_main_name_regex"}, {"n": "Thai Usulu Kaju Fıstıklı Tavuk", "p": {"getir": 839}, "k": "main", "ks": "r_main_name_regex"}, {"n": "Zencefil Soslu Çıtır Tavuk", "p": {"getir": 848}, "k": "main", "ks": "r_main_name_regex"}], "Tempuralar": [{"n": "Angry Shrimps (10 Adet)", "p": {"getir": 965}, "k": "other", "kc": 0.5}, {"n": "Fish & Cips", "p": {"getir": 965}, "k": "side", "ks": "r_side_tokens"}, {"n": "Karides & Sebzeli Tempura", "p": {"getir": 998}, "k": "other", "kc": 0.5}, {"n": "Kızarmış Halka Kalamar", "p": {"getir": 987}, "k": "side", "ks": "r_side_tokens"}, {"n": "Moğol Usulü Tavuk", "p": {"getir": 605}, "k": "main", "ks": "r_main_name_regex"}, {"n": "Tori Karaage", "p": {"getir": 603}, "k": "other", "kc": 0.5}, {"n": "Vietnam Usulü Susamlı Karides", "p": {"getir": 998}, "k": "other", "kc": 0.5}, {"n": "Çıtır Karides (10 Adet)", "p": {"getir": 881}, "k": "other", "kc": 0.5}], "Vejetaryen Rolls": [{"n": "Chuka Maki (6 Pcs.)", "p": {"getir": 578}, "k": "other", "kc": 0.5}, {"n": "Tofu Maki (6 Pcs.)", "p": {"getir": 576}, "k": "other", "kc": 0.5}, {"n": "Vegan Maki Roll (6 Pcs.)", "p": {"getir": 575}, "k": "other", "kc": 0.5}, {"n": "Vegan Tempura Roll (8 Pcs.)", "p": {"getir": 575}, "k": "other", "kc": 0.5}, {"n": "Vejetaryen Roll (8 adet)", "p": {"getir": 571}, "k": "other", "kc": 0.5}, {"n": "Wakame Vegan Roll (8 Pcs.)", "p": {"getir": 572}, "k": "other", "kc": 0.5}], "Çorbalar": [{"n": "Acılı Ekşili Çorba", "p": {"getir": 407}, "k": "main", "ks": "r_main_name_regex"}, {"n": "Deniz Ürünleri Çorbası", "p": {"getir": 486}, "k": "main", "ks": "r_main_strong_tokens"}, {"n": "Karidesli & Sebzeli Ramen Çorbası", "p": {"getir": 489}, "k": "main", "ks": "r_main_strong_tokens"}, {"n": "Miso Çorbası", "p": {"getir": 452}, "k": "main", "ks": "r_main_strong_tokens"}, {"n": "Sebze Çorbası", "p": {"getir": 405}, "k": "main", "ks": "r_main_strong_tokens"}, {"n": "Tavuklu Mısırlı Çorba", "p": {"getir": 407}, "k": "main", "ks": "r_main_name_regex"}, {"n": "Tavuklu Sebzeli Udon Çorba", "p": {"getir": 489}, "k": "main", "ks": "r_main_name_regex"}, {"n": "Tom Yum Çorba", "p": {"getir": 485}, "k": "main", "ks": "r_main_name_regex"}, {"n": "Wonton Çorbası", "p": {"getir": 452}, "k": "main", "ks": "r_main_strong_tokens"}], "Ördekler": [{"n": "Kızarmış Pekin Ördeği (Yarım)", "p": {"getir": 2740}, "k": "other", "kc": 0.5}, {"n": "Kızarmış Pekin Ördeği (Çeyrek)", "p": {"getir": 1438}, "k": "other", "kc": 0.5}, {"n": "Tatlı Ekşi Soslu Ördek", "p": {"getir": 1087}, "k": "other", "kc": 0.5}], "İçecekler": [{"n": "Cappy Karışık (330 ml)", "p": {"getir": 104}, "k": "drink", "ks": "noise:drink", "x": 1}, {"n": "Cappy Kayısı (330 ml)", "p": {"getir": 104}, "k": "drink", "ks": "noise:drink", "x": 1}, {"n": "Cappy Portakal (330 ml)", "p": {"getir": 104}, "k": "drink", "ks": "noise:drink", "x": 1}, {"n": "Cappy Vişne (330 ml)", "p": {"getir": 104}, "k": "drink", "ks": "noise:drink", "x": 1}, {"n": "Cappy Şeftali (330 ml)", "p": {"getir": 104}, "k": "drink", "ks": "noise:drink", "x": 1}, {"n": "Coca Cola (330 ml)", "p": {"getir": 104}, "k": "drink", "ks": "noise:drink", "x": 1}, {"n": "Coca Cola Light (330 ml)", "p": {"getir": 104}, "k": "drink", "ks": "noise:drink", "x": 1}, {"n": "Coca Cola Şekersiz (330 ml)", "p": {"getir": 104}, "k": "drink", "ks": "noise:drink", "x": 1}, {"n": "Fanta (330 ml)", "p": {"getir": 104}, "k": "drink", "ks": "noise:drink", "x": 1}, {"n": "Foco Liçi Meyveli (350 ml)", "p": {"getir": 118}, "k": "drink", "ks": "noise:drink", "x": 1}, {"n": "Foco Mangolu (350 ml)", "p": {"getir": 118}, "k": "drink", "ks": "noise:drink", "x": 1}, {"n": "Foco Çarkıfelek Meyveli (350 ml)", "p": {"getir": 118}, "k": "drink", "ks": "noise:drink", "x": 1}, {"n": "Fuse Tea Limon (330 ml)", "p": {"getir": 104}, "k": "drink", "ks": "noise:drink", "x": 1}, {"n": "Fuse Tea Şeftali (330 ml)", "p": {"getir": 104}, "k": "drink", "ks": "noise:drink", "x": 1}, {"n": "Ginger Walker's Zencefilli Gazoz (250 ml)", "p": {"getir": 118}, "k": "drink", "ks": "noise:drink", "x": 1}, {"n": "Schweppes Ginger Ale (250 ml)", "p": {"getir": 106}, "k": "drink", "ks": "noise:drink", "x": 1}, {"n": "Schweppes Mandalina (250 ml)", "p": {"getir": 106}, "k": "drink", "ks": "noise:drink", "x": 1}, {"n": "Soda (200 ml)", "p": {"getir": 83}, "k": "drink", "ks": "noise:drink", "x": 1}, {"n": "Sprite (330 ml)", "p": {"getir": 104}, "k": "drink", "ks": "noise:drink", "x": 1}, {"n": "Su (500 ml)", "p": {"getir": 76}, "k": "drink", "ks": "noise:drink", "x": 1}]}}