{"id": "gr_meshur-ci-borekci-1965-sehremini", "menu": {"Börek": [{"n": "Ispanaklı Çi Börek", "p": {"getir": 70}, "k": "bakery", "ks": "r_bakery_mcat"}, {"n": "Kaşarlı Çi Börek", "p": {"getir": 70}, "k": "bakery", "ks": "r_bakery_mcat"}, {"n": "Patatesli Çi Börek", "p": {"getir": 70}, "k": "bakery", "ks": "r_bakery_mcat"}, {"n": "Peynirli Çi Börek", "p": {"getir": 70}, "k": "bakery", "ks": "r_bakery_mcat"}, {"n": "Sucuk Kaşarlı Çi Börek", "p": {"getir": 100}, "k": "bakery", "ks": "r_bakery_mcat"}, {"n": "Çi Börek (10 Adet)", "p": {"getir": 700}, "k": "bakery", "ks": "r_bakery_mcat"}, {"n": "Çi Börek (20 Adet)", "p": {"getir": 1400}, "k": "bakery", "ks": "r_bakery_mcat"}, {"n": "Çi Börek (25 Adet)", "p": {"getir": 1600}, "k": "bakery", "ks": "r_bakery_mcat"}, {"n": "Çi Börek (30 Adet)", "p": {"getir": 1900}, "k": "bakery", "ks": "r_bakery_mcat"}, {"n": "Çi Börek (5 Adet)", "p": {"getir": 350}, "k": "bakery", "ks": "r_bakery_mcat"}, {"n": "Çi Börek (50 Adet)", "p": {"getir": 3000}, "k": "bakery", "ks": "r_bakery_mcat"}, {"n": "Çi Börek (Adet)", "p": {"getir": 70}, "k": "bakery", "ks": "r_bakery_mcat"}], "Gözleme": [{"n": "Ispanaklı Gözleme", "p": {"getir": 250}, "k": "main", "ks": "r_main_mcat"}, {"n": "Ispanaklı Kaşarlı Gözleme", "p": {"getir": 320}, "k": "main", "ks": "r_main_mcat"}, {"n": "Kavurmalı Kaşarlı Gözleme", "p": {"getir": 320}, "k": "main", "ks": "r_main_mcat"}, {"n": "Kaşar Peynirli Gözleme", "p": {"getir": 265}, "k": "main", "ks": "r_main_mcat"}, {"n": "Kıymalı Gözleme", "p": {"getir": 300}, "k": "main", "ks": "r_main_mcat"}, {"n": "Patatesli Gözleme", "p": {"getir": 265}, "k": "main", "ks": "r_main_mcat"}, {"n": "Patatesli Kaşarlı Gözleme", "p": {"getir": 300}, "k": "main", "ks": "r_main_mcat"}, {"n": "Peynirli Gözleme", "p": {"getir": 265}, "k": "main", "ks": "r_main_mcat"}, {"n": "Sucuklu Kaşarlı Gözleme", "p": {"getir": 300}, "k": "main", "ks": "r_main_mcat"}], "Kahvaltı": [{"n": "Kahvaltı Tabağı", "p": {"getir": 350}, "k": "breakfast", "ks": "r_breakfast_mcat"}, {"n": "Sucuklu Yumurta", "p": {"getir": 235}, "k": "breakfast", "ks": "r_breakfast_mcat"}, {"n": "Tereyağlı Sade Yumurta", "p": {"getir": 130}, "k": "breakfast", "ks": "r_breakfast_mcat"}], "Mantı": [{"n": "Mantı (1 kg)", "p": {"getir": 700}, "k": "main"}], "Poşet": [{"n": "Poşet", "p": {"getir": 0}, "k": "sauce", "ks": "noise:sauce", "x": 1}], "Çorba": [{"n": "Mercimek Çorbası", "p": {"getir": 160}, "k": "main", "ks": "r_main_mcat"}], "İçecek": [{"n": "Ayran (285 ml)", "p": {"getir": 100}, "k": "drink", "ks": "noise:drink", "x": 1}, {"n": "Beypazarı Soda (200 ml)", "p": {"getir": 30}, "k": "drink", "ks": "noise:drink", "x": 1}, {"n": "Coca Cola (330 ml)", "p": {"getir": 100}, "k": "drink", "ks": "noise:drink", "x": 1}, {"n": "Limonlu Soda (200 ml)", "p": {"getir": 40}, "k": "drink", "ks": "noise:drink", "x": 1}, {"n": "Su (500 ml)", "p": {"getir": 39}, "k": "drink", "ks": "noise:drink", "x": 1}]}}