{"id": "gr_pirpirim-gaziantep-mutfagi-merkezefendi-mah", "menu": {"Ara Sıcak": [{"n": "Fındık Lahmacun", "p": {"getir": 85}, "k": "main"}, {"n": "Kızartma İçli Köfte (Adet)", "p": {"getir": 170}, "k": "main"}, {"n": "Patates Cips", "p": {"getir": 160}, "x": 1, "k": "extra"}, {"n": "Peynirli Börek (Adet)", "p": {"getir": 100}, "k": "main"}], "Diğer Lezzet": [{"n": "Et Sote (180 g)", "p": {"getir": 750}, "k": "other"}, {"n": "Kilis Tava (200 g)", "p": {"getir": 750}, "k": "other"}, {"n": "Sac Tava (180 g)", "p": {"getir": 750}, "k": "other"}, {"n": "Tavuk Sac Tava (180 g)", "p": {"getir": 600}, "k": "main"}, {"n": "Tavuk Sote (180 g)", "p": {"getir": 600}, "k": "main"}, {"n": "Tavuk Çoban Kavurma (220 g)", "p": {"getir": 650}, "k": "main"}, {"n": "Çoban Kavurma (200 g)", "p": {"getir": 850}, "k": "other"}], "Dondurma": [{"n": "Özel Maraş Dondurması (155 g)", "p": {"getir": 120}, "k": "dessert", "x": 1}, {"n": "Özel Maraş Dondurması (90 g)", "p": {"getir": 100}, "k": "dessert", "x": 1}, {"n": "Özel Maraş Dondurması (Sade) (500 g)", "p": {"getir": 300}, "k": "dessert", "x": 1}, {"n": "Özel Maraş Dondurması (Çikolata & Fıstık & Sade) (500 g)", "p": {"getir": 320}, "k": "dessert", "x": 1}], "Dürüm (120 g)": [{"n": "Adana Dürüm", "p": {"getir": 350}, "k": "main"}, {"n": "Fıstıklı Kebap Dürüm", "p": {"getir": 450}, "k": "main"}, {"n": "Kuzu Şiş Dürüm", "p": {"getir": 450}, "k": "main"}, {"n": "Sebzeli Kebap Dürüm", "p": {"getir": 350}, "k": "main"}, {"n": "Tavuk Şiş Dürüm", "p": {"getir": 350}, "k": "main"}, {"n": "Urfa Dürüm", "p": {"getir": 350}, "k": "main"}, {"n": "Çöp Şiş Dürüm", "p": {"getir": 450}, "k": "main"}], "Fırından": [{"n": "Antep Lahmacun", "p": {"getir": 220}, "k": "main"}, {"n": "Karışık Pide", "p": {"getir": 500}, "k": "main"}, {"n": "Kavurmalı Kaşarlı Pide", "p": {"getir": 550}, "k": "main"}, {"n": "Kavurmalı Pide", "p": {"getir": 550}, "k": "main"}, {"n": "Kaşarlı Pide", "p": {"getir": 350}, "k": "main"}, {"n": "Kuşbaşı Tavuktan Pide", "p": {"getir": 350}, "k": "main"}, {"n": "Kuşbaşılı Kaşarlı Pide", "p": {"getir": 480}, "k": "main"}, {"n": "Kuşbaşılı Pide", "p": {"getir": 450}, "k": "main"}, {"n": "Kıymalı Pide", "p": {"getir": 350}, "k": "main"}, {"n": "Mantarlı Kaşarlı Pide", "p": {"getir": 380}, "k": "main"}, {"n": "Nar Ekşili Cevizli Lahmacun", "p": {"getir": 250}, "k": "main"}, {"n": "Sebzeli Kaşarlı Pide", "p": {"getir": 360}, "k": "main"}, {"n": "Sucuklu Kaşarlı Pide", "p": {"getir": 450}, "k": "main"}, {"n": "Tavuklu Kaşarlı Pide", "p": {"getir": 370}, "k": "main"}], "Kebap": [{"n": "Adana Kebap (160 g)", "p": {"getir": 520}, "k": "main"}, {"n": "Altı Ezmeli Kebap (Kıymadan)", "p": {"getir": 650}, "k": "main"}, {"n": "Domatesli Kebap", "p": {"getir": 650}, "k": "main"}, {"n": "Fıstıklı Kebap", "p": {"getir": 750}, "k": "main"}, {"n": "Kuzu Şiş Kebap (190 g)", "p": {"getir": 750}, "k": "main"}, {"n": "Mantarlı Kebap (180 g)", "p": {"getir": 650}, "k": "main"}, {"n": "Patlıcanlı Kebap (220 g)", "p": {"getir": 750}, "k": "main"}, {"n": "Pirpirim Karışık Kebap", "p": {"getir": 1200}, "k": "main"}, {"n": "Sarma Beyti Kebap (220 g)", "p": {"getir": 700}, "k": "main"}, {"n": "Sebzeli Kebap (160 g)", "p": {"getir": 520}, "k": "main"}, {"n": "Tavuk Kanat", "p": {"getir": 520}, "k": "main"}, {"n": "Tavuk Şiş (220 g)", "p": {"getir": 520}, "k": "main"}, {"n": "Urfa Kebap (160 g)", "p": {"getir": 520}, "k": "main"}, {"n": "Çöp Şiş Kebap (190 g)", "p": {"getir": 750}, "k": "main"}], "Salata": [{"n": "Abagannuş", "p": {"getir": 140}, "k": "other"}, {"n": "Antep Turşusu", "p": {"getir": 160}, "k": "other"}, {"n": "Cacık", "p": {"getir": 140}, "k": "other"}, {"n": "Göbek Salata", "p": {"getir": 180}, "x": 1, "k": "extra"}, {"n": "Karışık Salata", "p": {"getir": 180}, "x": 1, "k": "extra"}, {"n": "Mevsim Salata", "p": {"getir": 180}, "x": 1, "k": "extra"}, {"n": "Nurdağı Salata", "p": {"getir": 250}, "x": 1, "k": "extra"}, {"n": "Çoban Salata", "p": {"getir": 180}, "x": 1, "k": "extra"}], "Spesiyal Kebap": [{"n": "Alinazik Kebap (Kuzu Şişten) (190 g)", "p": {"getir": 800}, "k": "main"}, {"n": "Alinazik Kebap (Kıymadan)", "p": {"getir": 700}, "k": "main"}, {"n": "Kallavi (300 g)", "p": {"getir": 1000}, "k": "other"}, {"n": "Kilis Usulü Alinazik Kebap (Şişten)", "p": {"getir": 800}, "k": "main"}, {"n": "Kuzu Külbastı", "p": {"getir": 950}, "k": "other"}, {"n": "Pirpirim Sarma Kebap", "p": {"getir": 900}, "k": "main"}], "Tatlı": [{"n": "Fırın Sütlaç", "p": {"getir": 190}, "k": "dessert", "x": 1}, {"n": "Fıstıklı Kadayıf (Büyük)", "p": {"getir": 600}, "k": "dessert", "x": 1}, {"n": "Fıstıklı Kadayıf (Küçük)", "p": {"getir": 250}, "k": "dessert", "x": 1}, {"n": "Künefe (Büyük)", "p": {"getir": 500}, "k": "dessert", "x": 1}, {"n": "Künefe (Küçük)", "p": {"getir": 250}, "k": "dessert", "x": 1}], "Zeytinyağlı": [{"n": "Yoğurtlu Pirpirim", "p": {"getir": 140}, "k": "other"}, {"n": "Zeytinyağlı Abugannuş", "p": {"getir": 140}, "k": "other"}, {"n": "Çiğ Köfte (Etli)", "p": {"getir": 300}, "k": "main"}], "Çorba": [{"n": "Antep Yuvalama Çorbası", "p": {"getir": 300}, "k": "main"}, {"n": "Beyran Çorbası", "p": {"getir": 380}, "k": "main"}, {"n": "Ezogelin Çorbası", "p": {"getir": 150}, "k": "main"}, {"n": "Pirpirim Aşı", "p": {"getir": 250}, "k": "other"}], "İçecek": [{"n": "Ayran (300 ml)", "p": {"getir": 75}, "x": 1, "k": "drink"}, {"n": "Açık Ayran (1.5 L)", "p": {"getir": 190}, "x": 1, "k": "drink"}, {"n": "Cappy (330 ml)", "p": {"getir": 75}, "x": 1, "k": "drink"}, {"n": "Coca Cola (1 L)", "p": {"getir": 160}, "x": 1, "k": "drink"}, {"n": "Coca Cola (2.5 L)", "p": {"getir": 200}, "x": 1, "k": "drink"}, {"n": "Coca Cola (330 ml)", "p": {"getir": 75}, "x": 1, "k": "drink"}, {"n": "Coca Cola Şekersiz (330 ml)", "p": {"getir": 75}, "x": 1, "k": "drink"}, {"n": "Fanta (1 L)", "p": {"getir": 160}, "x": 1, "k": "drink"}, {"n": "Fanta (330 ml)", "p": {"getir": 75}, "x": 1, "k": "drink"}, {"n": "Soda (200 ml)", "p": {"getir": 40}, "x": 1, "k": "drink"}, {"n": "Sprite (330 ml)", "p": {"getir": 75}, "x": 1, "k": "drink"}, {"n": "Su (1.5 L)", "p": {"getir": 50}, "x": 1, "k": "drink"}, {"n": "Şalgam Suyu (330 ml)", "p": {"getir": 75}, "x": 1, "k": "drink"}]}}