{"id": "gr_selcuklu-lokantasi-bahcelievler-bahcelievler-", "menu": {"Ana Yemekler": [{"n": "Bulgur Pilavı", "p": {"getir": 120}, "k": "main", "ks": "r_main_mcat"}, {"n": "Etli Kuru Fasulye", "p": {"getir": 355}, "k": "main", "ks": "r_main_mcat"}, {"n": "Karnıyarık", "p": {"getir": 360}, "k": "main", "ks": "r_main_mcat"}, {"n": "Kavurma", "p": {"getir": 590}, "k": "main", "ks": "r_main_mcat"}, {"n": "Pirinç Pilavı", "p": {"getir": 120}, "k": "main", "ks": "r_main_mcat"}, {"n": "Sebze Yemeği", "p": {"getir": 320}, "k": "main", "ks": "r_main_mcat"}, {"n": "Tavuk Sote", "p": {"getir": 360}, "k": "main", "ks": "r_main_mcat"}, {"n": "Tavuk Yemeği", "p": {"getir": 360}, "k": "main", "ks": "r_main_mcat"}], "Mezeler": [{"n": "Cacık", "p": {"getir": 80}, "k": "side", "ks": "r_side_mcat"}, {"n": "Mevsim Salatası", "p": {"getir": 100}, "k": "extra", "ks": "noise:extra", "x": 1}], "Tatlılar": [{"n": "Hamsiköy Sütlacı", "p": {"getir": 200}, "k": "dessert", "ks": "r_dessert_mcat", "x": 1}, {"n": "Havuç Dilim Baklava", "p": {"getir": 300}, "k": "dessert", "ks": "r_dessert_mcat", "x": 1}], "Çorbalar": [{"n": "Kara Lahana Çorbası", "p": {"getir": 160}, "k": "main", "ks": "r_main_strong_tokens"}, {"n": "Mercimek Çorbası", "p": {"getir": 150}, "k": "main", "ks": "r_main_strong_tokens"}, {"n": "Tavuk Suyu Çorba", "p": {"getir": 150}, "k": "main", "ks": "r_main_name_regex"}], "İçecekler": [{"n": "Ateşoğlu Ayran (170 ml)", "p": {"getir": 50}, "k": "drink", "ks": "noise:drink", "x": 1}, {"n": "Ateşoğlu Ayran (270 ml)", "p": {"getir": 65}, "k": "drink", "ks": "noise:drink", "x": 1}, {"n": "Coca Cola (330 ml)", "p": {"getir": 80}, "k": "drink", "ks": "noise:drink", "x": 1}, {"n": "Fanta (330 ml)", "p": {"getir": 80}, "k": "drink", "ks": "noise:drink", "x": 1}, {"n": "Lipton Ice Tea Limon (330 ml)", "p": {"getir": 80}, "k": "drink", "ks": "noise:drink", "x": 1}, {"n": "Lipton Ice Tea Mango (330 ml)", "p": {"getir": 80}, "k": "drink", "ks": "noise:drink", "x": 1}, {"n": "Lipton Ice Tea Şeftali (330 ml)", "p": {"getir": 80}, "k": "drink", "ks": "noise:drink", "x": 1}, {"n": "Su (500 ml)", "p": {"getir": 45}, "k": "drink", "ks": "noise:drink", "x": 1}]}}