{"id": "gr_uskudar-tatlicisi-mimar-sinan-mah", "menu": {"Cedri Grolet & Fransız Tatlısı": [{"n": "Eşref Rüya", "p": {"getir": 400}, "k": "other"}, {"n": "Karanlık Rüya", "p": {"getir": 400}, "k": "other"}, {"n": "Milk Chocolate Truffles", "p": {"getir": 290}, "k": "other"}, {"n": "Saray Katmanı", "p": {"getir": 290}, "k": "other"}, {"n": "Xl Islak Rüya", "p": {"getir": 400}, "k": "other"}, {"n": "Yaz Esintisi", "p": {"getir": 350}, "k": "other"}], "Geleneksel Tatlı": [{"n": "Aşure", "p": {"getir": 200}, "k": "other"}, {"n": "Revani", "p": {"getir": 195}, "k": "other"}, {"n": "Çikolatalı Puding", "p": {"getir": 220}, "k": "other"}, {"n": "İrmik Tatlısı", "p": {"getir": 175}, "k": "other"}], "Pasta": [{"n": "Bisküvi Pastası", "p": {"getir": 195}, "k": "other"}, {"n": "Islak Kek", "p": {"getir": 195}, "k": "other"}, {"n": "Tiramisu", "p": {"getir": 250}, "k": "dessert", "x": 1}], "Special Tatlı": [{"n": "Belçika Duvarı", "p": {"getir": 290}, "k": "other"}, {"n": "Beyaz Rus", "p": {"getir": 290}, "k": "other"}, {"n": "Big Maccc", "p": {"getir": 300}, "k": "other"}, {"n": "Deep Mix", "p": {"getir": 290}, "k": "other"}, {"n": "Dubai Gecesi", "p": {"getir": 320}, "k": "other"}, {"n": "Frambuazlı Cheesecake", "p": {"getir": 250}, "k": "dessert", "x": 1}, {"n": "Kalpli Mono Pasta", "p": {"getir": 400}, "k": "other"}, {"n": "King Of The Forests", "p": {"getir": 275}, "k": "other"}, {"n": "Limonlu Cheesecake", "p": {"getir": 250}, "k": "dessert", "x": 1}, {"n": "Lotus Pasta", "p": {"getir": 350}, "k": "other"}, {"n": "San Sebastian Cheesecake", "p": {"getir": 290}, "k": "dessert", "x": 1}, {"n": "Special Sütlaç", "p": {"getir": 300}, "k": "dessert", "x": 1}, {"n": "Sufle", "p": {"getir": 330}, "k": "dessert", "x": 1}, {"n": "Yanık İspanyol Cheesecake", "p": {"getir": 290}, "k": "dessert", "x": 1}, {"n": "Çilekli Mag", "p": {"getir": 275}, "k": "other"}], "Sütlü Tatlı": [{"n": "Antep Fıstıklı Soğuk Kadayıf", "p": {"getir": 350}, "k": "dessert", "x": 1}, {"n": "Belçika Çikolatalı Triliçe (Dilim)", "p": {"getir": 175}, "k": "dessert", "x": 1}, {"n": "Frambuazlı Fıstıklı Soğuk Kadayıf", "p": {"getir": 350}, "k": "dessert", "x": 1}, {"n": "Frambuazlı Trileçe", "p": {"getir": 195}, "k": "dessert", "x": 1}, {"n": "Karamelli Trileçe", "p": {"getir": 195}, "k": "dessert", "x": 1}, {"n": "Kazandibi", "p": {"getir": 175}, "k": "dessert", "x": 1}, {"n": "Maraş Usulü Kesme Dondurma (Dilim)", "p": {"getir": 70}, "k": "dessert", "x": 1}, {"n": "Soğuk Baklava (3 Dilim)", "p": {"getir": 340}, "k": "dessert", "x": 1}, {"n": "Sütlaç", "p": {"getir": 175}, "k": "dessert", "x": 1}, {"n": "Çikolatalı Fıstıklı Soğuk Kadayıf", "p": {"getir": 350}, "k": "dessert", "x": 1}], "İçecek": [{"n": "Ayran (200 ml)", "p": {"getir": 60}, "x": 1, "k": "drink"}, {"n": "Ayran (290 ml)", "p": {"getir": 70}, "x": 1, "k": "drink"}, {"n": "Fruko (1 L)", "p": {"getir": 150}, "x": 1, "k": "drink"}, {"n": "Fruko (330 ml)", "p": {"getir": 95}, "x": 1, "k": "drink"}, {"n": "Lipton Ice Tea (330 ml)", "p": {"getir": 95}, "x": 1, "k": "drink"}, {"n": "Pepsi (1 L)", "p": {"getir": 150}, "x": 1, "k": "drink"}, {"n": "Pepsi (330 ml)", "p": {"getir": 95}, "x": 1, "k": "drink"}, {"n": "Pepsi Max (1 L)", "p": {"getir": 150}, "x": 1, "k": "drink"}, {"n": "Pepsi Max (330 ml)", "p": {"getir": 95}, "x": 1, "k": "drink"}, {"n": "Silivri Arslan Ayran (245 ml)", "p": {"getir": 95}, "x": 1, "k": "drink"}, {"n": "Su (330 ml)", "p": {"getir": 20}, "x": 1, "k": "drink"}, {"n": "Su (500 ml)", "p": {"getir": 40}, "x": 1, "k": "drink"}, {"n": "Yedigün (1 L)", "p": {"getir": 150}, "x": 1, "k": "drink"}, {"n": "Yedigün (330 ml)", "p": {"getir": 95}, "x": 1, "k": "drink"}, {"n": "Özerhisar Ayran (245 ml)", "p": {"getir": 95}, "x": 1, "k": "drink"}], "Şerbetli Tatlı": [{"n": "Ayva Tatlısı", "p": {"getir": 250}, "k": "other"}, {"n": "Kaymaklı Ekmek Kadayıf", "p": {"getir": 250}, "k": "bakery"}, {"n": "Kemalpaşa Tatlısı", "p": {"getir": 195}, "k": "other"}, {"n": "Kıbrıs Tatlısı", "p": {"getir": 195}, "k": "other"}]}}