{"id": "gr_yesilkoy-pilavcisi-yesilkoy-mah-bakirkoy", "menu": {"Menü": [{"n": "Duble Tavuklu Pilav Menü", "p": {"getir": 420}, "k": "combo", "ks": "r_combo_mcat"}, {"n": "Duble tavuklu pılav", "p": {"getir": 390}, "k": "combo", "ks": "r_combo_mcat"}, {"n": "Mega Çiğ Köfte Dürüm Menü", "p": {"getir": 187}, "k": "combo", "ks": "r_combo_mcat"}, {"n": "Nohutlu Pilav (Büyük Boy) Menü", "p": {"getir": 240}, "k": "combo", "ks": "r_combo_mcat"}, {"n": "Sporcu Menü (200 g pilav, 300 g tavuk)", "p": {"getir": 445}, "k": "combo", "ks": "r_combo_mcat"}, {"n": "Sporcu Menü Pilav (200 g) & Tavuk (200 g)", "p": {"getir": 338}, "k": "combo", "ks": "r_combo_mcat"}, {"n": "Sporcu Sadece Didiklenmiş Tavuk Menü (150 g)", "p": {"getir": 225}, "k": "combo", "ks": "r_combo_mcat"}, {"n": "Sporcu Yemeği Pilav (200 g) & Tavuk (500 g)", "p": {"getir": 740}, "k": "combo", "ks": "r_combo_mcat"}, {"n": "Sporcu ozel yemegı  200 pılav 400 gr tavuk", "p": {"getir": 545}, "k": "combo"}, {"n": "Tavuk & Ayran Menü 150 gr", "p": {"getir": 225}, "k": "combo"}, {"n": "Tavuk Dürüm Menü", "p": {"getir": 175}, "k": "combo", "ks": "r_combo_mcat"}, {"n": "Tavuklu Pilav (Büyük Boy) Menü", "p": {"getir": 287}, "k": "combo", "ks": "r_combo_mcat"}, {"n": "Çiğ Köfte Dürüm Menü", "p": {"getir": 185}, "k": "combo", "ks": "r_combo_mcat"}], "Meze": [{"n": "Zeytinyağlı Sarma (200 g)", "p": {"getir": 249}, "k": "main", "ks": "r_main_name_regex"}], "Pilav": [{"n": "Ekstra Ekstra Bol Tavuklu Pilav (Büyük Boy)", "p": {"getir": 291}, "k": "main", "ks": "r_main_mcat"}, {"n": "Nohutlu Pilav (Büyük Boy)", "p": {"getir": 205}, "k": "main", "ks": "r_main_mcat"}, {"n": "Nohutlu Pilav (Küçük Boy)", "p": {"getir": 181}, "k": "main", "ks": "r_main_mcat"}, {"n": "Spesiyal Didiklenmiş Tavuk (150 g)", "p": {"getir": 190}, "k": "main", "ks": "r_main_mcat"}, {"n": "Spesiyal Didiklenmiş Özel Tavuk (200 g)", "p": {"getir": 240}, "k": "main", "ks": "r_main_mcat"}, {"n": "Sporcu Yemeği (200 g) Sadece Özel Pişmiş", "p": {"getir": 245}, "k": "main", "ks": "r_main_mcat"}, {"n": "Sporcu Yemeği (300 g) Özel Pişmiş Sadece Tavuk", "p": {"getir": 333}, "k": "main", "ks": "r_main_mcat"}, {"n": "Sporcuya Özel Menü (200 g Pilav & 300 g Tavuk)", "p": {"getir": 400}, "k": "combo", "ks": "r_combo_name_price"}, {"n": "Sporcuya Özel Menü 150 Pilav & 200 Tavuk", "p": {"getir": 290}, "k": "combo", "ks": "r_combo_name_price"}, {"n": "Sporcuya Özel Pilav (150 g) & Tavuk (250 g)", "p": {"getir": 360}, "k": "main", "ks": "r_main_mcat"}, {"n": "Tavuklu Pilav (Büyük Boy)", "p": {"getir": 255}, "k": "main", "ks": "r_main_mcat"}, {"n": "Tavuklu Pilav (Küçük Boy)", "p": {"getir": 205}, "k": "main", "ks": "r_main_mcat"}], "Poşet": [{"n": "Poşet", "p": {"getir": 2}, "k": "sauce", "ks": "noise:sauce", "x": 1}], "Tatlı": [{"n": "Halka Tatlısı (Adet)", "p": {"getir": 50}, "k": "extra", "ks": "noise:extra", "x": 1}, {"n": "Tulumba (1 kg)", "p": {"getir": 750}, "k": "retail", "ks": "r_retail_name_token", "x": 1}, {"n": "Tulumba (500 g)", "p": {"getir": 445}, "k": "dessert", "ks": "r_dessert_mcat", "x": 1}, {"n": "Tulumba Tatlısı (Adet)", "p": {"getir": 35}, "k": "dessert", "ks": "r_dessert_mcat", "x": 1}], "Tavuk Dürüm": [{"n": "Tavuk Dürüm", "p": {"getir": 135}, "k": "main", "ks": "r_main_name_regex"}, {"n": "eksra bol tavuklu durum", "p": {"getir": 165}, "k": "main", "ks": "r_main_strong_tokens"}], "Çiğ Köfte": [{"n": "Mega Çiğ Köfte Dürüm", "p": {"getir": 160}, "k": "main", "ks": "r_main_name_regex"}, {"n": "Sushi Çiğ Köfte (240 g)", "p": {"getir": 276}, "k": "main", "ks": "r_main_name_regex"}, {"n": "Sushi Çiğ Köfte (480 g)", "p": {"getir": 428}, "k": "main", "ks": "r_main_name_regex"}, {"n": "Sushi Çiğ Köfte (720 g) 16 parca", "p": {"getir": 651}, "k": "main", "ks": "r_main_name_regex"}, {"n": "Çiğ Köfte (1 kg)", "p": {"getir": 984}, "k": "main"}, {"n": "Çiğ Köfte (200 g)", "p": {"getir": 259}, "k": "main", "ks": "r_main_name_regex"}, {"n": "Çiğ Köfte (400 g) (20 Sıkım)", "p": {"getir": 444}, "k": "main", "ks": "r_main_name_regex"}, {"n": "Çiğ Köfte (600 g) (28 Sıkım)", "p": {"getir": 633}, "k": "main", "ks": "r_main_name_regex"}, {"n": "Çiğ Köfte Dürüm", "p": {"getir": 153}, "k": "main", "ks": "r_main_name_regex"}], "İçecek": [{"n": "Acılı Ayran (200 ml)", "p": {"getir": 90}, "k": "drink", "ks": "noise:drink", "x": 1}, {"n": "Acılı Ayran (255 ml)", "p": {"getir": 86}, "k": "drink", "ks": "noise:drink", "x": 1}, {"n": "Ayran (1 L)", "p": {"getir": 130}, "k": "drink", "ks": "noise:drink", "x": 1}, {"n": "Ayran (200 ml)", "p": {"getir": 63}, "k": "drink", "ks": "noise:drink", "x": 1}, {"n": "Ayran (300 ml)", "p": {"getir": 76}, "k": "drink", "ks": "noise:drink", "x": 1}, {"n": "Coca Cola (1 L)", "p": {"getir": 144}, "k": "drink", "ks": "noise:drink", "x": 1}, {"n": "Coca Cola (330 ml)", "p": {"getir": 131}, "k": "drink", "ks": "noise:drink", "x": 1}, {"n": "Ekşili Ayran (270 ml)", "p": {"getir": 85}, "k": "drink", "ks": "noise:drink", "x": 1}, {"n": "Lipton Ice Tea Şeftali (330 ml)", "p": {"getir": 70}, "k": "drink", "ks": "noise:drink", "x": 1}, {"n": "Soda (200 ml)", "p": {"getir": 46}, "k": "drink", "ks": "noise:drink", "x": 1}, {"n": "Su (1.5 L)", "p": {"getir": 70}, "k": "drink", "ks": "noise:drink", "x": 1}, {"n": "Su (500 ml)", "p": {"getir": 35}, "k": "drink", "ks": "noise:drink", "x": 1}, {"n": "Şalgam Suyu (1 L)", "p": {"getir": 94}, "k": "drink", "ks": "noise:drink", "x": 1}, {"n": "Şalgam Suyu (300 ml)", "p": {"getir": 84}, "k": "drink", "ks": "noise:drink", "x": 1}]}}