{"id": "ty_367664", "menu": {"Coca-Cola Doyuran Menüleri": [{"n": "3 Lü Lahmacun Menü", "p": {"trendyol": 424}, "k": "combo", "ks": "r_combo_name_price"}, {"n": "Kavurmalı Kaşarlı Yumurtalı Pide Menü", "p": {"trendyol": 364}, "k": "combo", "ks": "r_combo_name_price"}, {"n": "Kuşbaşılı Pide Menü", "p": {"trendyol": 340}, "k": "combo", "ks": "r_combo_name_price"}, {"n": "Kıymalı Pide Menü", "p": {"trendyol": 292}, "k": "combo", "ks": "r_combo_name_price"}, {"n": "Malatya Lahmacunu Menü", "p": {"trendyol": 264}, "k": "combo", "ks": "r_combo_name_price"}], "Lahmacun": [{"n": "3 Lü Lahmacun", "p": {"trendyol": 340, "getir": 500}, "k": "main", "ks": "r_main_name_regex"}, {"n": "Karışık Lüx Paket", "p": {"trendyol": 840}, "k": "other", "kc": 0.5}], "Menüler": [{"n": "Kuşbaşılı Pide", "p": {"trendyol": 256, "getir": 400}, "k": "combo", "ks": "r_combo_mcat"}, {"n": "Kuşbaşılı kaşarlı pide", "p": {"trendyol": 288, "getir": 399}, "k": "combo", "ks": "r_combo_mcat"}], "Pideler": [{"n": "2 Lüx Menü", "p": {"trendyol": 520}, "k": "combo", "ks": "r_combo_name_price"}, {"n": "Tavuklu Pide", "p": {"trendyol": 256, "getir": 350}, "k": "main", "ks": "r_main_name_regex"}], "yemek": [{"n": "10'lu Lahmacun Menü", "p": {"trendyol": 1120, "getir": 1556}, "k": "combo", "ks": "r_combo_name_price"}, {"n": "5'li Lahmacun Menü", "p": {"trendyol": 640, "getir": 833}, "k": "combo", "ks": "r_combo_name_price"}, {"n": "Karışık Pide", "p": {"trendyol": 240, "getir": 300}, "k": "main", "ks": "r_main_mcat"}, {"n": "Karışık Yumurtalı Pide", "p": {"trendyol": 240}, "k": "main", "ks": "r_main_mcat"}, {"n": "Kavurmalı Kaşarlı Pide", "p": {"trendyol": 280}, "k": "main", "ks": "r_main_mcat"}, {"n": "Kavurmalı Kaşarlı Yumurtalı Pide", "p": {"trendyol": 280}, "k": "main", "ks": "r_main_mcat"}, {"n": "Kavurmalı Pide", "p": {"trendyol": 280}, "k": "main", "ks": "r_main_mcat"}, {"n": "Kaşarlı Pide", "p": {"trendyol": 240, "getir": 300}, "k": "main", "ks": "r_main_mcat"}, {"n": "Kaşarlı Sucuklu Yumurtalı Pide", "p": {"trendyol": 240}, "k": "main", "ks": "r_main_mcat"}, {"n": "Kaşarlı Yumurtalı Pide", "p": {"trendyol": 240, "getir": 300}, "k": "main", "ks": "r_main_mcat"}, {"n": "Kaşarlı katmer", "p": {"trendyol": 112, "getir": 175}, "k": "main", "ks": "r_main_mcat"}, {"n": "Kutu Ayran 330ml", "p": {"trendyol": 76}, "k": "drink", "ks": "noise:drink", "x": 1}, {"n": "Kutu Fanta 330ml", "p": {"trendyol": 84}, "k": "main", "ks": "r_main_mcat"}, {"n": "Kutu Kola 330ml", "p": {"trendyol": 84}, "k": "main", "ks": "r_main_mcat"}, {"n": "Kıymalı Katmer", "p": {"trendyol": 112, "getir": 175}, "k": "main", "ks": "r_main_mcat"}, {"n": "Kıymalı Kaşarlı Yumurtalı Pide", "p": {"trendyol": 240, "getir": 300}, "k": "main", "ks": "r_main_mcat"}, {"n": "Kıymalı Pide", "p": {"trendyol": 240, "getir": 300}, "k": "main", "ks": "r_main_mcat"}, {"n": "Kıymalı Yumurtalı Pide", "p": {"trendyol": 208, "getir": 300}, "k": "main", "ks": "r_main_mcat"}, {"n": "Lahmacun", "p": {"trendyol": 120, "getir": 150}, "k": "main", "ks": "r_main_mcat"}, {"n": "Lavaş", "p": {"trendyol": 24, "getir": 35}, "k": "extra", "ks": "noise:extra", "x": 1}, {"n": "Malatya Lahmacunu", "p": {"trendyol": 180, "getir": 300}, "k": "main", "ks": "r_main_mcat"}, {"n": "Sucuklu Kaşarlı Pide", "p": {"trendyol": 240, "getir": 350}, "k": "main", "ks": "r_main_mcat"}, {"n": "Sucuklu Pide", "p": {"trendyol": 240}, "k": "main", "ks": "r_main_mcat"}, {"n": "Tombik Ekmek", "p": {"trendyol": 24, "getir": 29}, "k": "bakery", "ks": "r_bakery_name_token"}, {"n": "Tırnaklı Pide", "p": {"trendyol": 48, "getir": 60}, "k": "main", "ks": "r_main_mcat"}, {"n": "Yağlı Katmer", "p": {"trendyol": 48, "getir": 50}, "k": "main", "ks": "r_main_mcat"}, {"n": "Çoban Pınar Su", "p": {"trendyol": 24}, "k": "drink", "ks": "noise:drink", "x": 1}], "İçecekler": [{"n": "Coca Cola 1Lt", "p": {"trendyol": 124, "getir": 156}, "k": "drink", "ks": "noise:drink", "x": 1}, {"n": "Fanta (1 lt.)", "p": {"trendyol": 128, "getir": 155}, "k": "drink", "ks": "noise:drink", "x": 1}, {"n": "Sütaş Ayran (1 lt.)", "p": {"trendyol": 128, "getir": 167}, "k": "drink", "ks": "noise:drink", "x": 1}], "Avantajlı Menü": [{"n": "3'lü Menü", "p": {"getir": 722}, "k": "combo", "ks": "r_combo_name_price"}], "Fırından Lezzet": [{"n": "Kavurma & Kaşar Peynirli Pide", "p": {"getir": 350}, "k": "bakery", "ks": "r_bakery_mcat"}], "İçecek": [{"n": "Ayran (300 ml)", "p": {"getir": 89}, "k": "drink", "ks": "noise:drink", "x": 1}, {"n": "Coca Cola (330 ml)", "p": {"getir": 130}, "k": "drink", "ks": "noise:drink", "x": 1}, {"n": "Coca Cola Zero Sugar (1 L)", "p": {"getir": 156}, "k": "drink", "ks": "noise:drink", "x": 1}, {"n": "Fanta (330 ml)", "p": {"getir": 130}, "k": "drink", "ks": "noise:drink", "x": 1}, {"n": "Pepsi (1 L)", "p": {"getir": 167}, "k": "drink", "ks": "noise:drink", "x": 1}]}}